openagentic_cli/__init__.py
openagentic_cli/__main__.py
openagentic_cli/args.py
openagentic_cli/auth_cmd.py
openagentic_cli/config.py
openagentic_cli/github_cmd.py
openagentic_cli/logs_cmd.py
openagentic_cli/mcp_cmd.py
openagentic_cli/permissions.py
openagentic_cli/repl.py
openagentic_cli/run_cmd.py
openagentic_cli/share_cmd.py
openagentic_cli/style.py
openagentic_cli/trace.py
openagentic_sdk/__init__.py
openagentic_sdk/__main__.py
openagentic_sdk/_version.py
openagentic_sdk/api.py
openagentic_sdk/auth.py
openagentic_sdk/client.py
openagentic_sdk/commands.py
openagentic_sdk/compaction.py
openagentic_sdk/custom_tools.py
openagentic_sdk/errors.py
openagentic_sdk/events.py
openagentic_sdk/js_plugins.py
openagentic_sdk/js_tools.py
openagentic_sdk/message_query.py
openagentic_sdk/messages.py
openagentic_sdk/opencode_config.py
openagentic_sdk/opencode_markdown.py
openagentic_sdk/options.py
openagentic_sdk/paths.py
openagentic_sdk/plugins.py
openagentic_sdk/prompt_system.py
openagentic_sdk/prompting.py
openagentic_sdk/runtime.py
openagentic_sdk/serialization.py
openagentic_sdk/console/__init__.py
openagentic_sdk/console/renderer.py
openagentic_sdk/console/run.py
openagentic_sdk/hooks/__init__.py
openagentic_sdk/hooks/engine.py
openagentic_sdk/hooks/models.py
openagentic_sdk/integrations/__init__.py
openagentic_sdk/integrations/acp.py
openagentic_sdk/integrations/acp_stdio.py
openagentic_sdk/integrations/github.py
openagentic_sdk/integrations/slack.py
openagentic_sdk/integrations/vscode.py
openagentic_sdk/js_runner/opencode_tool_runner.mjs
openagentic_sdk/lsp/__init__.py
openagentic_sdk/lsp/client.py
openagentic_sdk/lsp/config.py
openagentic_sdk/lsp/language.py
openagentic_sdk/lsp/manager.py
openagentic_sdk/lsp/protocol.py
openagentic_sdk/lsp/registry.py
openagentic_sdk/mcp/auth_store.py
openagentic_sdk/mcp/client.py
openagentic_sdk/mcp/credentials.py
openagentic_sdk/mcp/http_client.py
openagentic_sdk/mcp/oauth.py
openagentic_sdk/mcp/oauth_callback.py
openagentic_sdk-0.1.3.dist-info/METADATA
openagentic_sdk-0.1.3.dist-info/WHEEL
openagentic_sdk-0.1.3.dist-info/entry_points.txt
openagentic_sdk-0.1.3.dist-info/top_level.txt
openagentic_sdk-0.1.3.dist-info/RECORD
