Metadata-Version: 2.4
Name: openagentic-sdk
Version: 0.1.3
Summary: Open-source agent SDK (pure Python)
Author: openagentic-sdk contributors
Keywords: agent,cli,tools,repl
Classifier: Development Status :: 3 - Alpha
Classifier: Programming Language :: Python :: 3
Classifier: Programming Language :: Python :: 3 :: Only
Classifier: Programming Language :: Python :: 3.11
Classifier: Programming Language :: Python :: 3.12
Classifier: Operating System :: OS Independent
Requires-Python: >=3.11
Provides-Extra: dev
Requires-Dist: build>=1.2.0; extra == "dev"
Requires-Dist: twine>=5.0.0; extra == "dev"
Requires-Dist: ruff>=0.6.0; extra == "dev"
Requires-Dist: pre-commit>=3.7.0; extra == "dev"
